[
    {
        "topic": "ZDZICZENIE OBYCZAJÓW"
    },
    {
        "topic": "ŚWIAT NATURY"
    },
    {
        "topic": "JESIEŃ ŚREDNIOWIECZA"
    },
    {
        "topic": "GNUŚNY KARZEŁ"
    },
    {
        "topic": "ZAMOŻNY BEZDOMNY"
    },
    {
        "topic": "WOŹNA Z PODSTAWÓWKI"
    },
    {
        "topic": "PERSPEKTYWY W MIĘDZYBRODZIU"
    },
    {
        "topic": "WOLNE MIASTO MILICZ"
    },
    {
        "topic": "BAŁWAN Z KLASĄ"
    },
    {
        "topic": "DIETA PUDEŁKOWA"
    }
]